[{"s": "b57-bmv-motor", "t": "БМВ Б57 мотор: характеристики, ресурс и проблемы дизеля", "i": "📁", "c": "drugoe"}, {"s": "b57-bmw-dvigatel", "t": "Двигатель BMW B57: характеристики, проблемы и надежность", "i": "📁", "c": "drugoe"}, {"s": "b58-bmw-dvigatel-otzyvy", "t": "Двигатель BMW B58: честные отзывы владельцев и ресурс", "i": "📁", "c": "drugoe"}, {"s": "b58-motor-bmv", "t": "B58 мотор БМВ: Характеристики, ресурс, тюнинг и проблемы", "i": "📁", "c": "drugoe"}, {"s": "b57-bmw-dvigatel-obem-masla", "t": "Двигатель B57 BMW: Объем масла, характеристики и обслуживание", "i": "📁", "c": "drugoe"}, {"s": "b58-dvigatel-bmv", "t": "Двигатель BMW B58: характеристики, проблемы и тюнинг (2026)", "i": "📁", "c": "f30"}, {"s": "b58-motor-bmw", "t": "BMW B58: характеристики, проблемы и тюнинг мотора (2026)", "i": "📁", "c": "f30"}, {"s": "b52-dvigatel-bmw", "t": "Двигатель BMW B52: характеристики, проблемы и тюнинг", "i": "📁", "c": "e46"}, {"s": "b58-bmw-dvigatel", "t": "Двигатель B58 BMW: характеристики, проблемы и тюнинг (2026)", "i": "📁", "c": "e30"}, {"s": "b58-dvigatel-bmw", "t": "Двигатель BMW B58: Характеристики, Ресурс, Проблемы", "i": "📁", "c": "drugoe"}, {"s": "b58b30-dvigatel-bmw", "t": "Двигатель BMW B58B30: характеристики, проблемы и тюнинг мотора", "i": "📁", "c": "drugoe"}, {"s": "b57s-dvigatel-bmw", "t": "Двигатель BMW B57S: характеристики, проблемы и тюнинг дизеля", "i": "📁", "c": "drugoe"}, {"s": "b57-dvigatel-bmv", "t": "Двигатель BMW B57: характеристики, тюнинг и надежность", "i": "📁", "c": "drugoe"}, {"s": "b57-motor-bmv", "t": "Двигатель BMW B57: Технические характеристики, проблемы и ресурс", "i": "📁", "c": "drugoe"}]