[{"s": "m4-g82-bmv", "t": "BMW M4 G82: характеристики, особенности и тюнинг купе", "i": "📁", "c": "m4"}, {"s": "m4-kompetishn-bmv", "t": "BMW M4 Competition: Характеристики, обзор и отличия от G82", "i": "📁", "c": "m4"}, {"s": "m47-bmw-dvigatel", "t": "Двигатель BMW M47: характеристики, проблемы, ресурс", "i": "📁", "c": null}, {"s": "m4-bmv-kompetishen", "t": "BMW M4 Competition: характеристики, обзор и тесты", "i": "📁", "c": "m4"}, {"s": "m47-motor-bmv", "t": "М47 Мотор БМВ: Характеристики, Проблемы и Ресурс Двигателя", "i": "📁", "c": "e46"}, {"s": "m4-bmv-foto", "t": "BMW M4 (G82) — фото всех поколений и модификаций (2026)", "i": "📁", "c": "m4"}, {"s": "m4-bmv-kabriolet", "t": "BMW M4 Кабриолет: обзор, цены, характеристики и отзывы владельцев", "i": "📁", "c": "m4"}, {"s": "m4-bmv-saida", "t": "BMW M4 в кузове F82/F83 (Саида): технические особенности и тюнинг", "i": "📁", "c": "m4"}, {"s": "m4-foto-bmv", "t": "M4 Фото BMW: как сделать идеальные снимки купе 2026 года", "i": "📁", "c": "m4"}, {"s": "m42-dvigatel-bmv", "t": "Двигатель BMW M42: характеристики, проблемы и тюнинг", "i": "📁", "c": "e30"}, {"s": "m4-competition-bmw", "t": "BMW M4 Competition: Обзор, Характеристики и Динамика", "i": "📁", "c": "m4"}, {"s": "m4-f82-bmv", "t": "BMW M4 F82: характеристики, тюнинг и особенности купе", "i": "📁", "c": "m4"}, {"s": "m4-ks-bmv", "t": "BMW M4: характеристики, двигатели и обзор модели", "i": "📁", "c": "m4"}, {"s": "m4-kharakteristiki-bmv", "t": "BMW M4: полные характеристики, двигатели и динамика разгона", "i": "📁", "c": "m4"}, {"s": "m4-kupe-bmv", "t": "BMW M4 Coupe: Характеристики, двигатели и обзор купе", "i": "📁", "c": "m4"}, {"s": "m4-bmv-g82", "t": "BMW M4 G82: Характеристики, Двигатель и Отзывы Владельцев", "i": "📁", "c": "m4"}]