[{"s": "to-bmv-kh3", "t": "ТО БМВ Х3: Как провести техническое обслуживание BMW X3 своими руками", "i": "📁", "c": "x3"}, {"s": "to-bmw-x1-f48", "t": "BMW X1 F48: Полный обзор, характеристики и скрытые проблемы", "i": "📁", "c": "x1"}, {"s": "tojota-supra-bmv", "t": "Toyota Supra и BMW: Секреты легендарного союза A80 и Z4", "i": "📁", "c": "drugoe"}, {"s": "toplivnye-trubki-na-bmv-e39", "t": "Топливные трубки BMW E39: замена, размеры и диагностика", "i": "📁", "c": "e39"}, {"s": "toplivnyj-nasos-bmv-e60-n52", "t": "Топливный насос BMW E60 N52: признаки неисправности и замена", "i": "📁", "c": "e60"}, {"s": "tormoznye-diski-bmw-x1-f48", "t": "Тормозные диски BMW X1 F48: выбор, замена, артикулы", "i": "📁", "c": "x1"}, {"s": "tormoznye-diski-bmw", "t": "Тормозные диски BMW: выбор, замена и особенности", "i": "📁", "c": "drugoe"}, {"s": "toyota-supra-i-bmw-z4", "t": "Toyota Supra и BMW Z4: сравнение, отличия и выбор", "i": "📁", "c": "drugoe"}, {"s": "tojota-supra-i-bmv-z4", "t": "Toyota Supra vs BMW Z4: сравнение, технические данные и выбор", "i": "📁", "c": "z4"}, {"s": "top-bmv-dlya-drifta", "t": "Топ БМВ для дрифта: рейтинг лучших моделей и моторов", "i": "📁", "c": "drugoe"}, {"s": "tormoza-bmw-g30", "t": "Тормоза BMW G30: выбор, замена, размеры и прокачка системы", "i": "📁", "c": "g30"}, {"s": "tormoznoj-disk-bmw-x5", "t": "Тормозной диск BMW X5: выбор, артикулы, замена", "i": "📁", "c": "x5"}, {"s": "tormoznye-kolodki-bmv-e90", "t": "Тормозные колодки BMW E90: выбор, артикулы и замена", "i": "📁", "c": "e90"}, {"s": "toni-makhoni-bmv", "t": "Тони Махони BMW: история иконы автоспорта и его влияние", "i": "📁", "c": "drugoe"}, {"s": "toplivnyj-filtr-bmv-f30-benzin", "t": "Топливный фильтр BMW F30 бензин: выбор, замена, симптомы", "i": "📁", "c": "f30"}, {"s": "tormoznye-diski-bmv-e90", "t": "Тормозные диски BMW E90: размеры, выбор, замена", "i": "📁", "c": "e90"}, {"s": "to-na-bmv-kh5-dizel-tsena", "t": "BMW X5 дизель: цены 2026, сравнение поколений и скрытые расходы", "i": "📁", "c": "f15"}, {"s": "tochki-podklyucheniya-signalizatsii-bmv-e60", "t": "Точки подключения сигнализации BMW E60: схемы и инструкции", "i": "📁", "c": "e60"}, {"s": "tojota-ili-bmv", "t": "Тойота или БМВ: Что лучше выбрать в 2026 году?", "i": "📁", "c": "drugoe"}, {"s": "tonirovka-bmv-e90", "t": "Тонировка BMW E90: выбор пленки, законы и установка", "i": "📁", "c": "e90"}, {"s": "top-gir-mersedes-bmv-i-ford", "t": "Top Gear: Мерседес, БМВ и Форд — битва легенд", "i": "📁", "c": "drugoe"}, {"s": "top-nadyozhnykh-bmw", "t": "Топ надёжных BMW: какие модели не подведут?", "i": "📁", "c": "drugoe"}, {"s": "toplivnyj-filtr-bmw-e39", "t": "Топливный фильтр BMW E39: выбор, замена и симптомы", "i": "📁", "c": "e39"}, {"s": "tormoza-bmw-f30", "t": "Тормоза BMW F30: выбор, замена, тюнинг и диагностика", "i": "📁", "c": "f30"}, {"s": "tormoznye-diski-bmw-x7", "t": "Тормозные диски BMW X7: выбор, замена и признаки износа", "i": "📁", "c": "x7"}, {"s": "torpeda-ot-bmv-na-vaz-2107", "t": "Торпеда от BMW на ВАЗ 2107: полная инструкция по установке", "i": "📁", "c": "drugoe"}, {"s": "tochki-podklyucheniya-signalizatsii-bmv-e39", "t": "Точки подключения сигнализации BMW E39: схемы и места", "i": "📁", "c": "e39"}, {"s": "top-dvigatelej-bmv", "t": "Топ двигателей BMW: рейтинг надежных и мощных моторов", "i": "📁", "c": "drugoe"}, {"s": "top-nadezhnykh-bmv-s-probegom", "t": "ТОП надежных БМВ с пробегом: выбор эксперта", "i": "📁", "c": "drugoe"}, {"s": "top-nedorogikh-bmv", "t": "Топ недорогих БМВ: рейтинг лучших моделей до 1 млн", "i": "📁", "c": "drugoe"}, {"s": "tormoznaya-sistema-bmv-e39", "t": "Тормозная система BMW E39: ремонт, прокачка и тюнинг", "i": "📁", "c": "e39"}, {"s": "tormoznaya-sistema-bmw", "t": "Тормозная система BMW: устройство, неисправности и обслуживание", "i": "📁", "c": "f30"}, {"s": "to-bmw-g20", "t": "BMW G20: Полный обзор 3-й серии 7-го поколения", "i": "📁", "c": "g20"}, {"s": "toplivnyj-nasos-bmv-e39", "t": "Топливный насос BMW E39: неисправности, замена, выбор запчастей", "i": "📁", "c": "e39"}, {"s": "topovaya-muzyka-v-bmv", "t": "Топовая музыка в BMW: настройка звука, форматы и системы", "i": "📁", "c": "drugoe"}, {"s": "tormoznaya-zhidkost-bmv-e39", "t": "Тормозная жидкость BMW E39: выбор, замена, прокачка", "i": "📁", "c": "e39"}, {"s": "tormoznye-kolodki-bmv-e46", "t": "Тормозные колодки BMW E46: выбор, замена и артикулы", "i": "📁", "c": "e46"}, {"s": "torpeda-bmv-e46", "t": "Торпеда BMW E46: устройство, ремонт и тюнинг (фото + схемы)", "i": "📁", "c": "e46"}, {"s": "toplivnye-trubki-bmv-e39", "t": "Топливные трубки BMW E39: выбор, замена, диагностика", "i": "📁", "c": "e39"}, {"s": "toplivnyj-filtr-bmv-kh6", "t": "Топливный фильтр BMW X6: выбор, замена, симптомы", "i": "📁", "c": "x6"}, {"s": "tormoznye-kolodki-bmv-e60", "t": "Тормозные колодки BMW E60: выбор, замена, артикулы и советы", "i": "📁", "c": "e60"}, {"s": "top-krasivykh-bmv", "t": "Топ-10 самых красивых BMW: от классики до суперкаров 2026 года", "i": "📁", "c": "drugoe"}, {"s": "top-nadezhnykh-bmv", "t": "Топ-10 надежных BMW: рейтинг 2026 по отзывам владельцев и экспертов", "i": "📁", "c": "e46"}, {"s": "toplivnyj-filtr-bmv-kh1-e84-dizel", "t": "Топливный фильтр BMW X1 E84 дизель: выбор, замена, ошибки", "i": "📁", "c": "x1"}, {"s": "tormoznye-diski-bmw-x3-f25", "t": "Тормозные диски BMW X3 F25: выбор, замена и особенности", "i": "📁", "c": "f25"}, {"s": "tormoznye-diski-na-bmv-kh5-e70", "t": "Тормозные диски BMW X5 E70: выбор, замена и нюансы эксплуатации", "i": "📁", "c": "e70"}, {"s": "tormoznye-trubki-bmv-e39-zadnie", "t": "Задние тормозные трубки BMW E39: выбор, замена, нюансы", "i": "📁", "c": "e39"}, {"s": "torpeda-bmv-e60", "t": "Торпеда BMW E60: особенности, ремонт и тюнинг (2003-2010)", "i": "📁", "c": "e60"}, {"s": "torpedo-bmv-e34", "t": "Торпедо BMW E34: особенности, ремонт и тюнинг (фото + цены)", "i": "📁", "c": "e34"}, {"s": "toplivnyj-filtr-bmv-e39", "t": "Топливный фильтр BMW E39: замена, артикулы и симптомы", "i": "📁", "c": "e39"}, {"s": "tormoznye-diski-na-bmv-f30", "t": "Тормозные диски на BMW F30: выбор, размеры, замена", "i": "📁", "c": "f30"}, {"s": "torpeda-bmv-e36", "t": "Торпеда БМВ Е36: ремонт, разборка и устранение трещин", "i": "📁", "c": "e36"}, {"s": "toplivnyj-filtr-dlya-bmv", "t": "Топливный фильтр для BMW: выбор, замена и симптомы", "i": "📁", "c": null}, {"s": "torpeda-bmv-e30", "t": "Торпеда BMW E30: особенности, тюнинг и ремонт (1982-1994)", "i": "📁", "c": "e30"}, {"s": "tolshchina-lkp-bmv", "t": "Толщина ЛКП БМВ: эталонные значения и допуски по кузовам", "i": "📁", "c": "drugoe"}, {"s": "toplivnyj-nasos-bmv", "t": "Топливный насос БМВ: признаки неисправности и замена", "i": "📁", "c": "drugoe"}, {"s": "tormoznoj-disk-bmv-e39", "t": "Тормозные диски BMW E39: выбор, замена и особенности модели", "i": "📁", "c": "e39"}, {"s": "tormoznye-diski-na-bmv", "t": "Тормозные диски на BMW: выбор, замена, артикулы", "i": "📁", "c": "drugoe"}, {"s": "toyota-supra-bmw", "t": "Toyota Supra и BMW: История союза и сравнение двигателей", "i": "📁", "c": "drugoe"}, {"s": "top-10-bmv", "t": "Топ-10 BMW всех времён: легенды, которые изменили автоиндустрию", "i": "📁", "c": "drugoe"}, {"s": "toplivnyj-filtr-bmw-e46", "t": "Топливный фильтр BMW E46: выбор, замена и диагностика", "i": "📁", "c": "e46"}, {"s": "tort-bmw-m5", "t": "Торт BMW M5: как испечь легендарный автомобильный десерт", "i": "📁", "c": "m5"}, {"s": "tormoznoj-disk-bmv", "t": "Тормозной диск BMW: выбор, артикулы, замена и диагностика", "i": "📁", "c": "drugoe"}, {"s": "tormoznye-trubki-bmv-e46", "t": "Тормозные трубки BMW E46: выбор, замена и диагностика неисправностей", "i": "📁", "c": "e46"}, {"s": "top-luchshikh-bmv", "t": "Топ-10 лучших BMW всех времён: рейтинг 2026 года с ценами", "i": "📁", "c": "drugoe"}, {"s": "tormoza-na-bmv", "t": "Тормоза на BMW: признаки неисправностей и ремонт своими руками", "i": "📁", "c": "e60"}, {"s": "tormoznye-diski-na-bmv-kh3-f25", "t": "Тормозные диски на БМВ Х3 F25: выбор, замена и артикулы", "i": "📁", "c": "f25"}, {"s": "tormoznye-kolodki-bmv-e39", "t": "Тормозные колодки БМВ Е39: выбор, замена и артикулы", "i": "📁", "c": "e39"}, {"s": "toplivnyj-bak-bmv-e34", "t": "Топливный бак BMW E34: особенности, ремонт и замена", "i": "📁", "c": "e34"}, {"s": "toplivnyj-filtr-bmv-e60", "t": "Топливный фильтр BMW E60: выбор, замена и симптомы", "i": "📁", "c": "e60"}, {"s": "tormoznye-diski-bmv-kh3-f25-kupit", "t": "Тормозные диски BMW X3 F25 купить: цены, артикулы, выбор", "i": "📁", "c": "x3"}, {"s": "tormoznye-kolodki-bmw-g30", "t": "Тормозные колодки BMW G30: выбор, артикулы и замена", "i": "📁", "c": null}, {"s": "toplivnyj-filtr-bmv-e46", "t": "Топливный фильтр BMW E46: выбор, замена и нюансы (2026)", "i": "📁", "c": "e46"}, {"s": "toplivnyj-nasos-bmv-e34", "t": "Топливный насос BMW E34: признаки неисправности и замена", "i": "📁", "c": "e34"}, {"s": "tormoznye-kolodki-bmv-kh5-e53", "t": "Тормозные колодки BMW X5 E53: выбор, артикулы, замена", "i": "📁", "c": "x5"}, {"s": "torpeda-bmv-e34", "t": "Торпеда BMW E34: особенности, ремонт и тюнинг панели приборов", "i": "📁", "c": "e34"}, {"s": "toplivnyj-filtr-bmv-e34", "t": "Топливный фильтр BMW E34: когда менять и какой выбрать", "i": "📁", "c": "e34"}, {"s": "toplivnyj-filtr-bmv-e36", "t": "Топливный фильтр БМВ Е36: замена, артикулы и диагностика", "i": "📁", "c": "e36"}, {"s": "tormoznaya-sistema-bmv", "t": "Тормозная система БМВ: Устройство, диагностика и обслуживание", "i": "📁", "c": "drugoe"}, {"s": "tormoznye-diski-bmv-e39-perednie", "t": "Тормозные диски BMW E39: выбор, замена и особенности передние", "i": "📁", "c": "e39"}, {"s": "tormoznye-diski-na-bmv-g30", "t": "Тормозные диски на BMW G30: выбор, замена, особенности", "i": "📁", "c": "g30"}, {"s": "tormoznye-kolodki-bmw-x3-g01", "t": "Тормозные колодки BMW X3 G01: выбор, замена, особенности", "i": "📁", "c": "x3"}, {"s": "top-mashin-bmv", "t": "Топ-10 BMW 2026: лучшие модели по цене, мощности и надежности", "i": "📁", "c": "m5"}, {"s": "toplivnyj-filtr-bmv-e90", "t": "Топливный фильтр BMW E90: замена, выбор, признаки неисправности", "i": "📁", "c": "e90"}, {"s": "tormoznye-diski-bmv-kh5-e70", "t": "Тормозные диски BMW X5 E70: выбор, замена, особенности", "i": "📁", "c": "e70"}, {"s": "tormoznye-diski-bmv-kh5", "t": "Тормозные диски BMW X5: выбор, замена и особенности для F15/G05", "i": "📁", "c": "f15"}, {"s": "tormoznye-nakladki-bmv-chto-eto", "t": "Тормозные накладки BMW: что это, как выбрать и заменить", "i": "📁", "c": "drugoe"}, {"s": "top-samykh-nadezhnykh-bmv", "t": "ТОП-10 самых надежных BMW: рейтинг 2026 по отзывам владельцев", "i": "📁", "c": "e39"}, {"s": "toplivnyj-filtr-bmv-dizel", "t": "Топливный фильтр BMW дизель: замена, выбор, признаки неисправности", "i": "📁", "c": "e90"}, {"s": "tormoznaya-zhidkost-bmw-g30", "t": "Тормозная жидкость BMW G30: выбор, замена и нюансы для 5 серии", "i": "📁", "c": "g30"}, {"s": "tormoznye-kolodki-bmw-f10", "t": "Тормозные колодки BMW F10: выбор, замена и особенности (2026)", "i": "📁", "c": "f10"}, {"s": "top-gir-bmv-m5-e60", "t": "Топ-гир BMW M5 E60: тюнинг, мощность и цены 2026 года", "i": "📁", "c": "e60"}, {"s": "top-gir-gonka-24-chasa-na-bmv", "t": "Топ Гир: гонка 24 часа на BMW — подготовка, тактика и секреты победы", "i": "📁", "c": "m3"}, {"s": "toplivnyj-filtr-bmw-f30-320d", "t": "Топливный фильтр BMW F30 320d: выбор, замена, особенности", "i": "📁", "c": "f30"}, {"s": "tormoza-na-bmw-f30", "t": "Тормоза BMW F30: неисправности, диагностика и ремонт", "i": "📁", "c": "f30"}, {"s": "tormoznye-diski-na-bmv-e60", "t": "Тормозные диски BMW E60: выбор, замена, нюансы (2026)", "i": "📁", "c": "e60"}, {"s": "torpedo-bmv-e90", "t": "Торпедо BMW E90: выбор, замена и тюнинг (2026 гайд)", "i": "📁", "c": "e90"}, {"s": "to-po-reglamentu-oelservice-bmw-chto-eto", "t": "Регламент OELSERVICE BMW: расшифровка и интервалы", "i": "📁", "c": "drugoe"}, {"s": "tormoza-bmw-f30-m-performance", "t": "Тормоза BMW F30 M Performance: Обзор, установка и отзывы", "i": "📁", "c": "f30"}, {"s": "tormoznaya-zhidkost-dlya-bmv-f30", "t": "Тормозная жидкость для BMW F30: выбор, замена, ошибки", "i": "📁", "c": "f30"}, {"s": "tormoznoj-disk-bmv-e60", "t": "Тормозной диск BMW E60: выбор, размеры и замена", "i": "📁", "c": "e60"}, {"s": "tormoznye-kolodki-bmw-x1-f48", "t": "Тормозные колодки BMW X1 F48: выбор, замена и артикулы", "i": "📁", "c": "x1"}, {"s": "top-byudzhetnykh-bmv", "t": "Топ-10 бюджетных BMW: лучшие модели до 1 500 000 ₽ в 2026 году", "i": "📁", "c": "e46"}, {"s": "toplivnyj-filtr-bmv-kh3-g01-dizel", "t": "Топливный фильтр BMW X3 G01 дизель: замена, выбор, сроки", "i": "📁", "c": "x3"}, {"s": "tormoznye-diski-bmv-e34-kupit", "t": "Тормозные диски BMW E34: как выбрать и где купить оригинал", "i": "📁", "c": "e34"}, {"s": "toplivnyj-nasos-bmv-f10", "t": "Топливный насос BMW F10: признаки неисправности и замена", "i": "📁", "c": "f10"}, {"s": "torpeda-bmv-3", "t": "Торпеда BMW 3 серии: особенности, тюнинг и ремонт", "i": "📁", "c": "e46"}, {"s": "tormoznaya-zhidkost-bmv-kh5-e70", "t": "Тормозная жидкость BMW X5 E70: выбор, замена, особенности", "i": "📁", "c": "e70"}, {"s": "tormoznye-diski-bmv-e36", "t": "Тормозные диски BMW E36: выбор, замена, особенности (2026)", "i": "📁", "c": "e36"}, {"s": "toplivnyj-filtr-bmv-e60-m54", "t": "Топливный фильтр BMW E60 (M54): выбор, замена, нюансы", "i": "📁", "c": "e60"}, {"s": "tormoznye-diski-bmw-f30-320i", "t": "Тормозные диски BMW F30 320i: выбор, замена, особенности", "i": "📁", "c": "f30"}, {"s": "tormoznye-kolodki-bmv-kh5", "t": "Тормозные колодки BMW X5: выбор, замена, особенности для E53/F15/G05", "i": "📁", "c": "f15"}, {"s": "tormoznye-kolodki-na-bmv-kh5-g05", "t": "Тормозные колодки BMW X5 G05: выбор, замена, особенности", "i": "📁", "c": "g05"}, {"s": "tormoznye-diski-bmv-g30-520-d", "t": "Тормозные диски BMW G30 520d: выбор, замена, ресурс", "i": "📁", "c": "g30"}, {"s": "tormoznoj-disk-bmv-e46", "t": "Тормозные диски BMW E46: выбор, замена и особенности модели", "i": "📁", "c": "e46"}, {"s": "top-bmv-mashin", "t": "Топ BMW 2026: лучшие модели по цене, мощности и надежности", "i": "📁", "c": "drugoe"}, {"s": "toplivnyj-nasos-bmv-kh5-e70-dizel", "t": "Топливный насос BMW X5 E70 дизель: неисправности и ремонт", "i": "📁", "c": "e70"}, {"s": "tormoznye-diski-bmv-e46", "t": "Тормозные диски BMW E46: выбор, замена и нюансы эксплуатации", "i": "📁", "c": "e46"}, {"s": "to-na-bmv-kh5", "t": "Что такое кнопка «ТО» на BMW X5: функции, ошибки и сброс", "i": "📁", "c": "f15"}, {"s": "toplivnyj-filtr-bmv", "t": "Топливный фильтр BMW: выбор, замена и последствия", "i": "📁", "c": "drugoe"}, {"s": "toplivnyj-nasos-bmv-e36", "t": "Топливный насос BMW E36: выбор, диагностика и замена", "i": "📁", "c": "e36"}, {"s": "tormoznaya-zhidkost-v-bmv", "t": "Тормозная жидкость в BMW: выбор, замена, допуски DOT 4", "i": "📁", "c": "drugoe"}, {"s": "tormoznye-diski-bmv-e46-perednie", "t": "Тормозные диски BMW E46 передние: выбор, замена и размеры", "i": "📁", "c": "e46"}, {"s": "tormoznye-diski-bmw-x3", "t": "Тормозные диски BMW X3: выбор, замена и диагностика", "i": "📁", "c": "x3"}, {"s": "tormoznye-kolodki-na-bmw-x5-f15", "t": "Тормозные колодки BMW X5 F15: выбор, замена и ресурс", "i": "📁", "c": "x5"}, {"s": "tormoznye-trubki-bmv-e39", "t": "Тормозные трубки БМВ Е39: размеры, замена и прокачка", "i": "📁", "c": "e39"}, {"s": "tormoznaya-zhidkost-bmv-original", "t": "Оригинальная тормозная жидкость BMW: выбор, замена, особенности", "i": "📁", "c": "f30"}, {"s": "tormoznye-diski-bmw-x5", "t": "Тормозные диски BMW X5: выбор, замена, особенности (E53, E70, F15, G05)", "i": "📁", "c": "x5"}, {"s": "tormoznye-kolodki-bmw-f30", "t": "Тормозные колодки BMW F30: выбор, замена и особенности", "i": "📁", "c": "f30"}, {"s": "tormoznye-diski-bmv-e60", "t": "Тормозные диски BMW E60: выбор, замена и особенности (2026)", "i": "📁", "c": "e60"}, {"s": "toplivnyj-filtr-bmv-g30-520d", "t": "Топливный фильтр BMW G30 520d: замена, выбор, ресурс", "i": "📁", "c": "g30"}, {"s": "tormoznye-kolodki-bmv-kh7", "t": "Тормозные колодки BMW X7: выбор, замена, ресурс и советы экспертов", "i": "📁", "c": "x7"}, {"s": "toplivnyj-filtr-bmw-f30", "t": "Топливный фильтр BMW F30: замена, выбор, признаки неисправности", "i": "📁", "c": "f30"}, {"s": "toplivnyj-filtr-bmv-kh1-e84-benzin", "t": "Топливный фильтр BMW X1 E84 бензин: замена, выбор, признаки неисправности", "i": "📁", "c": "x1"}, {"s": "tochki-podklyucheniya-signalizatsii-bmv-kh5-e53", "t": "Точки подключения сигнализации БМВ Х5 Е53: схема, CAN-шина и CANtr", "i": "📁", "c": "e53"}, {"s": "toni-makhouni-bmv", "t": "Тони Махоуни BMW: история легендарного мастера кузовного ремонта", "i": "📁", "c": "drugoe"}, {"s": "tormoznye-diski-bmv-e39", "t": "Тормозные диски BMW E39: выбор, замена, нюансы эксплуатации", "i": "📁", "c": "e39"}, {"s": "tormoznye-diski-bmv-kh3-g01", "t": "Тормозные диски BMW X3 G01: выбор, размеры, артикулы", "i": "📁", "c": "x3"}, {"s": "torpeda-bmw-e30", "t": "BMW E30 «Торпеда»: разбор, тюнинг и ремонт приборной панели", "i": "📁", "c": "e30"}, {"s": "tovarnyj-znak-bmv", "t": "Товарный знак BMW: история, значение и юридическая защита", "i": "📁", "c": "drugoe"}, {"s": "tormoznye-diski-bmw-f10", "t": "Тормозные диски BMW F10: выбор, замена и нюансы эксплуатации", "i": "📁", "c": "f10"}, {"s": "tormoznye-diski-bmv", "t": "Тормозные диски BMW: выбор, замена и особенности для разных моделей", "i": "📁", "c": "e90"}, {"s": "tormoznye-kolodki-bmw-g20", "t": "Тормозные колодки BMW G20: выбор, замена, ресурс и советы эксперта", "i": "📁", "c": "g20"}, {"s": "to-bmv-kh1", "t": "BMW X1 (F48, U11): технические характеристики, цены и отзывы 2026", "i": "📁", "c": "x1"}, {"s": "toplivnyj-nasos-bmv-e39-m52", "t": "Топливный насос BMW E39 M52: признаки неисправности и замена", "i": "📁", "c": "e39"}, {"s": "to-na-bmv-kh1", "t": "Что такое «ТО» на BMW X1: полное руководство для владельцев", "i": "📁", "c": "x1"}, {"s": "toplivnyj-filtr-bmv-e65", "t": "Топливный фильтр BMW E65: выбор, замена, нюансы 2026", "i": "📁", "c": "e65"}, {"s": "tormoznye-kolodki-bmv-e34", "t": "Тормозные колодки BMW E34: выбор, замена и нюансы (2026)", "i": "📁", "c": "e34"}, {"s": "torpedo-bmv-e60", "t": "Торпедо BMW E60: особенности, ремонт и тюнинг (2026 гайд)", "i": "📁", "c": "e60"}, {"s": "toplivnyj-filtr-bmv-kh5-f15-dizel", "t": "Топливный фильтр BMW X5 F15 дизель: замена, выбор, признаки неисправности", "i": "📁", "c": "f15"}, {"s": "tormoznaya-zhidkost-bmw-f30", "t": "Тормозная жидкость BMW F30: выбор, замена, особенности", "i": "📁", "c": "f30"}, {"s": "tool32-bmw-skachat", "t": "Tool32 BMW скачать: полная инструкция по установке и настройке", "i": "📁", "c": "drugoe"}, {"s": "top-gir-bmv-m5", "t": "Топ-гир BMW M5: лучшие поколения и тюнинг-рецепты (2026)", "i": "📁", "c": "m5"}, {"s": "top-gir-bmv-mersedes-ford", "t": "BMW против Mercedes против Ford: Битва Топ Гир", "i": "📁", "c": "drugoe"}, {"s": "toplivnyj-bak-bmv-e38", "t": "Топливный бак BMW E38: ремонт, замена, симптомы проблем", "i": "📁", "c": "e38"}, {"s": "toplivnyj-filtr-bmv-e39-gde-nakhoditsya", "t": "Топливный фильтр БМВ Е39: где находится и как заменить", "i": "📁", "c": "e39"}, {"s": "tormoznoj-disk-bmv-e34", "t": "Тормозной диск БМВ Е34: выбор, артикулы, размеры", "i": "📁", "c": "e34"}, {"s": "tormoznye-diski-bmv-f10", "t": "Тормозные диски БМВ F10: выбор, размеры, замена и диагностика", "i": "📁", "c": "f10"}, {"s": "torpeda-bmv-f30", "t": "Торпеда BMW F30: особенности, ремонт и тюнинг (2012-2019)", "i": "📁", "c": "f30"}, {"s": "to-bmv-kh5-g05", "t": "ТО BMW X5 G05: коды ошибок, выбор жидкости, интервалы замены", "i": "📁", "c": "g05"}, {"s": "tool32-bmw-instruktsiya", "t": "Tool32 BMW: Полная инструкция, установка и коды ошибок", "i": "📁", "c": "drugoe"}, {"s": "toplivnyj-nasos-bmv-e46", "t": "Топливный насос БМВ Е46: признаки неисправности и замена", "i": "📁", "c": "e46"}, {"s": "tojota-supra-i-bmv", "t": "Тойота Супра и BMW: История альянса, отличия и сравнение", "i": "📁", "c": "drugoe"}, {"s": "top-nadezhnykh-dvigatelej-bmv", "t": "Топ надежных двигателей BMW: Рейтинг лучших моторов", "i": "📁", "c": "drugoe"}, {"s": "top-starykh-bmv", "t": "Топ старых БМВ: какие модели E30, E36, E39 и E46 выбрать", "i": "📁", "c": "drugoe"}, {"s": "toplivnaya-trubka-bmv-e34", "t": "Топливная трубка BMW E34: диагностика, замена и ремонт", "i": "📁", "c": "e34"}, {"s": "toplivnaya-sistema-bmv-e39", "t": "Топливная система БМВ Е39: диагностика, ремонт и устройство", "i": "📁", "c": "e39"}, {"s": "tormoznaya-zhidkost-bmw-x5-g05", "t": "Тормозная жидкость BMW X5 G05: спецификации, замена и выбор", "i": "📁", "c": "g05"}, {"s": "tormoznye-nakladki-na-bmv", "t": "Тормозные накладки BMW: выбор, замена и артикулы", "i": "📁", "c": "drugoe"}]