[{"s": "x5-iz-bumera-2", "t": "X5 из бумера 2: Реально ли превратить BMW E39 в E53", "i": "📁", "c": "e39"}, {"s": "x5-iz-bumera", "t": "X5 из Бумера: Реально ли превратить E39/E60 в BMW X5?", "i": "📁", "c": "x5"}, {"s": "x5-bmw-vse-pokoleniya", "t": "BMW X5: все поколения (E53, E70, F15, F85, G05) — история, особенности, сравнение", "i": "📁", "c": "x5"}, {"s": "x5-bmw-e70", "t": "BMW X5 E70: Технические характеристики, двигатели и отзывы", "i": "📁", "c": "x5"}, {"s": "x5-bmw-e53", "t": "BMW X5 E53: Обзор легенды, технические данные и скрытые проблемы", "i": "📁", "c": "x5"}, {"s": "x5-bmv-kupit-bu", "t": "BMW X5 б/у: как купить без рисков и не переплатить в 2026 году", "i": "📁", "c": "x5"}, {"s": "x5-bmw-narxi", "t": "BMW X5 (G05) 2026: цены в Узбекистане, комплектации, сравнение", "i": "📁", "c": "x5"}, {"s": "x5-bmw-novaya", "t": "BMW X5 2026: новая модель — цены, комплектации и тест-драйв", "i": "📁", "c": "x5"}, {"s": "x5-davidycha-bmw", "t": "X5 Давидыча BMW: обзор, технические характеристики и история", "i": "📁", "c": null}, {"s": "x5-iz-filma-bumer", "t": "BMW X5 из фильма Бумер: история культового авто", "i": "📁", "c": "e53"}]